{
  "$schema": "http://cyclonedx.org/schema/bom-1.6.schema.json",
  "version": 1,
  "metadata": {
    "tools": [
      {
        "name": "trivy",
        "vendor": "aquasecurity",
        "version": "unknown"
      }
    ],
    "component": {
      "name": "python",
      "purl": "pkg:oci/python@3.9-slim-buster?digest=sha256:320a7a4250aba4249f458872adecf92eea88dc6abd2d76dc5c0f01cac9b53990",
      "type": "library",
      "bom-ref": "pkg:oci/python@3.9-slim-buster?digest=sha256:320a7a4250aba4249f458872adecf92eea88dc6abd2d76dc5c0f01cac9b53990",
      "version": "3.9-slim-buster"
    },
    "timestamp": "2025-01-01T13:12:59.442888+00:00"
  },
  "bomFormat": "CycloneDX",
  "components": [
    {
      "name": "adduser",
      "type": "library",
      "bom-ref": "BomRef.4106548171771164.40345315035365337",
      "version": "3.118"
    },
    {
      "name": "apt",
      "type": "library",
      "bom-ref": "BomRef.5764489436016302.11966297497559053",
      "version": "1.8.2.3"
    },
    {
      "name": "ba8c79bf-2683-4450-98a2-ba1a95df72bb",
      "type": "library",
      "bom-ref": "BomRef.6176396336955146.7344873491266293",
      "version": "unknown"
    },
    {
      "name": "base-files",
      "type": "library",
      "bom-ref": "BomRef.2091561318312628.10533641099039537",
      "version": "10.3+deb10u13"
    },
    {
      "name": "base-passwd",
      "type": "library",
      "bom-ref": "BomRef.5285899786206747.39893870367851547",
      "version": "3.5.46"
    },
    {
      "name": "bash",
      "type": "library",
      "bom-ref": "BomRef.19632902380378148.7674190403644553",
      "version": "5.0-4"
    },
    {
      "name": "bsdutils",
      "type": "library",
      "bom-ref": "BomRef.08044540296163805.6074878777255607",
      "version": "1:2.33.1-0.1"
    },
    {
      "name": "ca-certificates",
      "type": "library",
      "bom-ref": "BomRef.19697092205222.4114747644816703",
      "version": "20200601~deb10u2"
    },
    {
      "name": "coreutils",
      "type": "library",
      "bom-ref": "BomRef.7835375189870991.9714073481058098",
      "version": "8.30-3"
    },
    {
      "name": "dash",
      "type": "library",
      "bom-ref": "BomRef.123298693870599.28454743690470186",
      "version": "0.5.10.2-5"
    },
    {
      "name": "debconf",
      "type": "library",
      "bom-ref": "BomRef.21872175349675793.21978558774826173",
      "version": "1.5.71+deb10u1"
    },
    {
      "name": "debian",
      "type": "library",
      "bom-ref": "BomRef.7231334427763637.7970442731868245",
      "version": "10.13"
    },
    {
      "name": "debian-archive-keyring",
      "type": "library",
      "bom-ref": "BomRef.49943365452815924.574184867203909",
      "version": "2019.1+deb10u1"
    },
    {
      "name": "debianutils",
      "type": "library",
      "bom-ref": "BomRef.007838730168462704.04960075241039086",
      "version": "4.8.6.1"
    },
    {
      "name": "diffutils",
      "type": "library",
      "bom-ref": "BomRef.9381702685953822.8704276567702453",
      "version": "1:3.7-3"
    },
    {
      "name": "dpkg",
      "type": "library",
      "bom-ref": "BomRef.39041126673773086.5934036822798651",
      "version": "1.19.8"
    },
    {
      "name": "e2fsprogs",
      "type": "library",
      "bom-ref": "BomRef.8087205421834798.12970919873885822",
      "version": "1.44.5-1+deb10u3"
    },
    {
      "name": "fdisk",
      "type": "library",
      "bom-ref": "BomRef.13779902434842395.07571395197316111",
      "version": "2.33.1-0.1"
    },
    {
      "name": "findutils",
      "type": "library",
      "bom-ref": "BomRef.23493549977876682.8226606810817382",
      "version": "4.6.0+git+20190209-2"
    },
    {
      "name": "gcc-8-base",
      "type": "library",
      "bom-ref": "BomRef.3950435385749209.9713751141431759",
      "version": "8.3.0-6"
    },
    {
      "name": "gpgv",
      "type": "library",
      "bom-ref": "BomRef.5231310262223396.6296323553660003",
      "version": "2.2.12-1+deb10u2"
    },
    {
      "name": "grep",
      "type": "library",
      "bom-ref": "BomRef.6944009531744872.423455455135313",
      "version": "3.3-1"
    },
    {
      "name": "gzip",
      "type": "library",
      "bom-ref": "BomRef.06246220426837246.38047467679875757",
      "version": "1.9-3+deb10u1"
    },
    {
      "name": "hostname",
      "type": "library",
      "bom-ref": "BomRef.3159739788366621.9573437779759497",
      "version": "3.21"
    },
    {
      "name": "init-system-helpers",
      "type": "library",
      "bom-ref": "BomRef.5484736261483107.35607144113402145",
      "version": "1.56+nmu1"
    },
    {
      "name": "libacl1",
      "type": "library",
      "bom-ref": "BomRef.3170287804189975.8581828672652744",
      "version": "2.2.53-4"
    },
    {
      "name": "libapt-pkg5.0",
      "type": "library",
      "bom-ref": "BomRef.7589394888738071.5676067692913361",
      "version": "1.8.2.3"
    },
    {
      "name": "libattr1",
      "type": "library",
      "bom-ref": "BomRef.31741350102540533.13132463919420412",
      "version": "1:2.4.48-4"
    },
    {
      "name": "libaudit-common",
      "type": "library",
      "bom-ref": "BomRef.9711466857540676.2231529081764385",
      "version": "1:2.8.4-3"
    },
    {
      "name": "libaudit1",
      "type": "library",
      "bom-ref": "BomRef.4285357051314367.28625519667125443",
      "version": "1:2.8.4-3"
    },
    {
      "name": "libblkid1",
      "type": "library",
      "bom-ref": "BomRef.4717716494577069.31419335513246105",
      "version": "2.33.1-0.1"
    },
    {
      "name": "libbz2-1.0",
      "type": "library",
      "bom-ref": "BomRef.3022033642181272.10541805158756778",
      "version": "1.0.6-9.2~deb10u2"
    },
    {
      "name": "libc-bin",
      "type": "library",
      "bom-ref": "BomRef.8074508612901721.5349819479162559",
      "version": "2.28-10+deb10u2"
    },
    {
      "name": "libc6",
      "type": "library",
      "bom-ref": "BomRef.8170352054673204.45266508153759977",
      "version": "2.28-10+deb10u2"
    },
    {
      "name": "libcap-ng0",
      "type": "library",
      "bom-ref": "BomRef.7970489706159132.7621623219385009",
      "version": "0.7.9-2"
    },
    {
      "name": "libcom-err2",
      "type": "library",
      "bom-ref": "BomRef.8661478586184156.7845309765155044",
      "version": "1.44.5-1+deb10u3"
    },
    {
      "name": "libdb5.3",
      "type": "library",
      "bom-ref": "BomRef.8226914678415594.25588819524503914",
      "version": "5.3.28+dfsg1-0.5"
    },
    {
      "name": "libdebconfclient0",
      "type": "library",
      "bom-ref": "BomRef.6611298573963369.5741563291771412",
      "version": "0.249"
    },
    {
      "name": "libexpat1",
      "type": "library",
      "bom-ref": "BomRef.09728070518796805.6425828489493881",
      "version": "2.2.6-2+deb10u6"
    },
    {
      "name": "libext2fs2",
      "type": "library",
      "bom-ref": "BomRef.7800340428531145.7613589707345659",
      "version": "1.44.5-1+deb10u3"
    },
    {
      "name": "libfdisk1",
      "type": "library",
      "bom-ref": "BomRef.8734399927920087.007389040746614839",
      "version": "2.33.1-0.1"
    },
    {
      "name": "libffi6",
      "type": "library",
      "bom-ref": "BomRef.03135848170111033.07351886946086106",
      "version": "3.2.1-9"
    },
    {
      "name": "libgcc1",
      "type": "library",
      "bom-ref": "BomRef.2661655399555968.26106285153227726",
      "version": "1:8.3.0-6"
    },
    {
      "name": "libgcrypt20",
      "type": "library",
      "bom-ref": "BomRef.48183529112695056.5379591155799494",
      "version": "1.8.4-5+deb10u1"
    },
    {
      "name": "libgdbm6",
      "type": "library",
      "bom-ref": "BomRef.6113324167968318.26932352046523056",
      "version": "1.18.1-4"
    },
    {
      "name": "libgmp10",
      "type": "library",
      "bom-ref": "BomRef.7533192798023765.14660906261556617",
      "version": "2:6.1.2+dfsg-4+deb10u1"
    },
    {
      "name": "libgnutls30",
      "type": "library",
      "bom-ref": "BomRef.2642346134690531.07941861698216335",
      "version": "3.6.7-4+deb10u10"
    },
    {
      "name": "libgpg-error0",
      "type": "library",
      "bom-ref": "BomRef.14447900021030913.5050481265260169",
      "version": "1.35-1"
    },
    {
      "name": "libhogweed4",
      "type": "library",
      "bom-ref": "BomRef.589653529997073.5229953429927768",
      "version": "3.4.1-1+deb10u1"
    },
    {
      "name": "libidn2-0",
      "type": "library",
      "bom-ref": "BomRef.8117423853886457.4648140235794761",
      "version": "2.0.5-1+deb10u1"
    },
    {
      "name": "liblz4-1",
      "type": "library",
      "bom-ref": "BomRef.6851599695313291.08990890399812401",
      "version": "1.8.3-1+deb10u1"
    },
    {
      "name": "liblzma5",
      "type": "library",
      "bom-ref": "BomRef.843847496965296.7511672660256941",
      "version": "5.2.4-1+deb10u1"
    },
    {
      "name": "libmount1",
      "type": "library",
      "bom-ref": "BomRef.21307869203310903.5315082586911285",
      "version": "2.33.1-0.1"
    },
    {
      "name": "libncursesw6",
      "type": "library",
      "bom-ref": "BomRef.8981094158029495.9035551035035969",
      "version": "6.1+20181013-2+deb10u3"
    },
    {
      "name": "libnettle6",
      "type": "library",
      "bom-ref": "BomRef.14816770679843028.3553849695854441",
      "version": "3.4.1-1+deb10u1"
    },
    {
      "name": "libp11-kit0",
      "type": "library",
      "bom-ref": "BomRef.2272886416556048.12388153118869705",
      "version": "0.23.15-2+deb10u1"
    },
    {
      "name": "libpam-modules",
      "type": "library",
      "bom-ref": "BomRef.2667887207665496.7341866808898544",
      "version": "1.3.1-5"
    },
    {
      "name": "libpam-modules-bin",
      "type": "library",
      "bom-ref": "BomRef.8469338240067857.047269724613064446",
      "version": "1.3.1-5"
    },
    {
      "name": "libpam-runtime",
      "type": "library",
      "bom-ref": "BomRef.12837962734449626.05534387675259855",
      "version": "1.3.1-5"
    },
    {
      "name": "libpam0g",
      "type": "library",
      "bom-ref": "BomRef.5345454605247784.20220601551008066",
      "version": "1.3.1-5"
    },
    {
      "name": "libpcre3",
      "type": "library",
      "bom-ref": "BomRef.41206197383737364.3468607874589076",
      "version": "2:8.39-12"
    },
    {
      "name": "libreadline7",
      "type": "library",
      "bom-ref": "BomRef.7696861557576261.3318395440957952",
      "version": "7.0-5"
    },
    {
      "name": "libseccomp2",
      "type": "library",
      "bom-ref": "BomRef.2683506269789242.7243998880253915",
      "version": "2.3.3-4"
    },
    {
      "name": "libselinux1",
      "type": "library",
      "bom-ref": "BomRef.6429455295562106.7064314295365873",
      "version": "2.8-1+b1"
    },
    {
      "name": "libsemanage-common",
      "type": "library",
      "bom-ref": "BomRef.1825685027184697.005724517540941831",
      "version": "2.8-2"
    },
    {
      "name": "libsemanage1",
      "type": "library",
      "bom-ref": "BomRef.9137893926473654.9865446889174417",
      "version": "2.8-2"
    },
    {
      "name": "libsepol1",
      "type": "library",
      "bom-ref": "BomRef.3978305772391917.14039325714478323",
      "version": "2.8-1"
    },
    {
      "name": "libsmartcols1",
      "type": "library",
      "bom-ref": "BomRef.27152506136280485.1935197351032666",
      "version": "2.33.1-0.1"
    },
    {
      "name": "libsqlite3-0",
      "type": "library",
      "bom-ref": "BomRef.5506495027418566.2784048376638487",
      "version": "3.27.2-3+deb10u2"
    },
    {
      "name": "libss2",
      "type": "library",
      "bom-ref": "BomRef.7795371118756164.3457972843468424",
      "version": "1.44.5-1+deb10u3"
    },
    {
      "name": "libssl1.1",
      "type": "library",
      "bom-ref": "BomRef.9414875880166151.4959548383628055",
      "version": "1.1.1n-0+deb10u5"
    },
    {
      "name": "libstdc++6",
      "type": "library",
      "bom-ref": "BomRef.9312106539908698.23572848170581295",
      "version": "8.3.0-6"
    },
    {
      "name": "libsystemd0",
      "type": "library",
      "bom-ref": "BomRef.5417366821428413.1438590947874785",
      "version": "241-7~deb10u9"
    },
    {
      "name": "libtasn1-6",
      "type": "library",
      "bom-ref": "BomRef.15062815171974941.724007452379435",
      "version": "4.13-3+deb10u1"
    },
    {
      "name": "libtinfo6",
      "type": "library",
      "bom-ref": "BomRef.7841101856428094.49191235980057746",
      "version": "6.1+20181013-2+deb10u3"
    },
    {
      "name": "libudev1",
      "type": "library",
      "bom-ref": "BomRef.5445025828491711.48712032812716544",
      "version": "241-7~deb10u9"
    },
    {
      "name": "libunistring2",
      "type": "library",
      "bom-ref": "BomRef.3954637679877454.4215398480724897",
      "version": "0.9.10-1"
    },
    {
      "name": "libuuid1",
      "type": "library",
      "bom-ref": "BomRef.7845302580394067.5391425268250879",
      "version": "2.33.1-0.1"
    },
    {
      "name": "libzstd1",
      "type": "library",
      "bom-ref": "BomRef.1100663801705305.9598521082996869",
      "version": "1.3.8+dfsg-3+deb10u2"
    },
    {
      "name": "login",
      "type": "library",
      "bom-ref": "BomRef.7310717039694602.29386248113252045",
      "version": "1:4.5-1.1"
    },
    {
      "name": "mawk",
      "type": "library",
      "bom-ref": "BomRef.47805142558440994.27285780335907417",
      "version": "1.3.3-17+b3"
    },
    {
      "name": "mount",
      "type": "library",
      "bom-ref": "BomRef.3830330187021158.6044547888756708",
      "version": "2.33.1-0.1"
    },
    {
      "name": "ncurses-base",
      "type": "library",
      "bom-ref": "BomRef.3083430203319103.9208606227334225",
      "version": "6.1+20181013-2+deb10u3"
    },
    {
      "name": "ncurses-bin",
      "type": "library",
      "bom-ref": "BomRef.4469121080242916.1622680119779809",
      "version": "6.1+20181013-2+deb10u3"
    },
    {
      "name": "netbase",
      "type": "library",
      "bom-ref": "BomRef.25440448789280723.4391424255841939",
      "version": "5.6"
    },
    {
      "name": "openssl",
      "type": "library",
      "bom-ref": "BomRef.6268911726585615.04840601523020027",
      "version": "1.1.1n-0+deb10u5"
    },
    {
      "name": "passwd",
      "type": "library",
      "bom-ref": "BomRef.6846444710357533.8024111595128504",
      "version": "1:4.5-1.1"
    },
    {
      "name": "perl-base",
      "type": "library",
      "bom-ref": "BomRef.6220556903779093.005414770566189664",
      "version": "5.28.1-6+deb10u1"
    },
    {
      "name": "pip",
      "type": "library",
      "bom-ref": "BomRef.403700319377266.12738586110437944",
      "version": "23.0.1"
    },
    {
      "name": "pkg:deb/debian/adduser@3.118?arch=all&distro=debian-10.13",
      "type": "library",
      "bom-ref": "BomRef.9243611090117512.47714167587276113",
      "version": "unknown"
    },
    {
      "name": "pkg:deb/debian/apt@1.8.2.3?arch=amd64&distro=debian-10.13",
      "type": "library",
      "bom-ref": "BomRef.5274394552679859.8445427415265542",
      "version": "unknown"
    },
    {
      "name": "pkg:deb/debian/base-files@10.3%2Bdeb10u13?arch=amd64&distro=debian-10.13",
      "type": "library",
      "bom-ref": "BomRef.2967330057897104.5040741558506687",
      "version": "unknown"
    },
    {
      "name": "pkg:deb/debian/base-passwd@3.5.46?arch=amd64&distro=debian-10.13",
      "type": "library",
      "bom-ref": "BomRef.9861438969360008.5012638479741188",
      "version": "unknown"
    },
    {
      "name": "pkg:deb/debian/bash@5.0-4?arch=amd64&distro=debian-10.13",
      "type": "library",
      "bom-ref": "BomRef.8522141329258298.9346347482229125",
      "version": "unknown"
    },
    {
      "name": "pkg:deb/debian/bsdutils@2.33.1-0.1?arch=amd64&distro=debian-10.13&epoch=1",
      "type": "library",
      "bom-ref": "BomRef.9431523444773862.48301525597665396",
      "version": "unknown"
    },
    {
      "name": "pkg:deb/debian/ca-certificates@20200601~deb10u2?arch=all&distro=debian-10.13",
      "type": "library",
      "bom-ref": "BomRef.07781830204959628.04339280253173139",
      "version": "unknown"
    },
    {
      "name": "pkg:deb/debian/coreutils@8.30-3?arch=amd64&distro=debian-10.13",
      "type": "library",
      "bom-ref": "BomRef.8661634751568574.9339051917710173",
      "version": "unknown"
    },
    {
      "name": "pkg:deb/debian/dash@0.5.10.2-5?arch=amd64&distro=debian-10.13",
      "type": "library",
      "bom-ref": "BomRef.936449302980033.8545499211546351",
      "version": "unknown"
    },
    {
      "name": "pkg:deb/debian/debconf@1.5.71%2Bdeb10u1?arch=all&distro=debian-10.13",
      "type": "library",
      "bom-ref": "BomRef.7526493208645537.02383917188472129",
      "version": "unknown"
    },
    {
      "name": "pkg:deb/debian/debian-archive-keyring@2019.1%2Bdeb10u1?arch=all&distro=debian-10.13",
      "type": "library",
      "bom-ref": "BomRef.0006152465802201634.4631536434983474",
      "version": "unknown"
    },
    {
      "name": "pkg:deb/debian/debianutils@4.8.6.1?arch=amd64&distro=debian-10.13",
      "type": "library",
      "bom-ref": "BomRef.7207167623331593.45235921348010955",
      "version": "unknown"
    },
    {
      "name": "pkg:deb/debian/diffutils@3.7-3?arch=amd64&distro=debian-10.13&epoch=1",
      "type": "library",
      "bom-ref": "BomRef.2728436378390051.9249776559314489",
      "version": "unknown"
    },
    {
      "name": "pkg:deb/debian/dpkg@1.19.8?arch=amd64&distro=debian-10.13",
      "type": "library",
      "bom-ref": "BomRef.2897300372502959.9312535430593759",
      "version": "unknown"
    },
    {
      "name": "pkg:deb/debian/e2fsprogs@1.44.5-1%2Bdeb10u3?arch=amd64&distro=debian-10.13",
      "type": "library",
      "bom-ref": "BomRef.6838340901315719.9157372342516404",
      "version": "unknown"
    },
    {
      "name": "pkg:deb/debian/fdisk@2.33.1-0.1?arch=amd64&distro=debian-10.13",
      "type": "library",
      "bom-ref": "BomRef.684453649653739.6597726156523075",
      "version": "unknown"
    },
    {
      "name": "pkg:deb/debian/findutils@4.6.0%2Bgit%2B20190209-2?arch=amd64&distro=debian-10.13",
      "type": "library",
      "bom-ref": "BomRef.7116479712211018.7517733506180486",
      "version": "unknown"
    },
    {
      "name": "pkg:deb/debian/gcc-8-base@8.3.0-6?arch=amd64&distro=debian-10.13",
      "type": "library",
      "bom-ref": "BomRef.07281602366116657.6243025962737354",
      "version": "unknown"
    },
    {
      "name": "pkg:deb/debian/gpgv@2.2.12-1%2Bdeb10u2?arch=amd64&distro=debian-10.13",
      "type": "library",
      "bom-ref": "BomRef.18183696370020264.4088028993540581",
      "version": "unknown"
    },
    {
      "name": "pkg:deb/debian/grep@3.3-1?arch=amd64&distro=debian-10.13",
      "type": "library",
      "bom-ref": "BomRef.5722608417861503.6527072754481692",
      "version": "unknown"
    },
    {
      "name": "pkg:deb/debian/gzip@1.9-3%2Bdeb10u1?arch=amd64&distro=debian-10.13",
      "type": "library",
      "bom-ref": "BomRef.431931804549218.06703505513618213",
      "version": "unknown"
    },
    {
      "name": "pkg:deb/debian/hostname@3.21?arch=amd64&distro=debian-10.13",
      "type": "library",
      "bom-ref": "BomRef.6905480172641373.11068904079134823",
      "version": "unknown"
    },
    {
      "name": "pkg:deb/debian/init-system-helpers@1.56%2Bnmu1?arch=all&distro=debian-10.13",
      "type": "library",
      "bom-ref": "BomRef.9267275828375128.6770824946557062",
      "version": "unknown"
    },
    {
      "name": "pkg:deb/debian/libacl1@2.2.53-4?arch=amd64&distro=debian-10.13",
      "type": "library",
      "bom-ref": "BomRef.9174858123595855.07159214189561325",
      "version": "unknown"
    },
    {
      "name": "pkg:deb/debian/libapt-pkg5.0@1.8.2.3?arch=amd64&distro=debian-10.13",
      "type": "library",
      "bom-ref": "BomRef.9123630239172172.4772858501637405",
      "version": "unknown"
    },
    {
      "name": "pkg:deb/debian/libattr1@2.4.48-4?arch=amd64&distro=debian-10.13&epoch=1",
      "type": "library",
      "bom-ref": "BomRef.28673386609622875.11670208602889987",
      "version": "unknown"
    },
    {
      "name": "pkg:deb/debian/libaudit-common@2.8.4-3?arch=all&distro=debian-10.13&epoch=1",
      "type": "library",
      "bom-ref": "BomRef.31296870280502054.3681329725059911",
      "version": "unknown"
    },
    {
      "name": "pkg:deb/debian/libaudit1@2.8.4-3?arch=amd64&distro=debian-10.13&epoch=1",
      "type": "library",
      "bom-ref": "BomRef.13420312221791275.9566188980831586",
      "version": "unknown"
    },
    {
      "name": "pkg:deb/debian/libblkid1@2.33.1-0.1?arch=amd64&distro=debian-10.13",
      "type": "library",
      "bom-ref": "BomRef.06788697139426092.30307873955849707",
      "version": "unknown"
    },
    {
      "name": "pkg:deb/debian/libbz2-1.0@1.0.6-9.2~deb10u2?arch=amd64&distro=debian-10.13",
      "type": "library",
      "bom-ref": "BomRef.4776024341063957.7550766671423965",
      "version": "unknown"
    },
    {
      "name": "pkg:deb/debian/libc-bin@2.28-10%2Bdeb10u2?arch=amd64&distro=debian-10.13",
      "type": "library",
      "bom-ref": "BomRef.29299669173162535.8957049923898667",
      "version": "unknown"
    },
    {
      "name": "pkg:deb/debian/libc6@2.28-10%2Bdeb10u2?arch=amd64&distro=debian-10.13",
      "type": "library",
      "bom-ref": "BomRef.5965573119036772.9456242921041607",
      "version": "unknown"
    },
    {
      "name": "pkg:deb/debian/libcap-ng0@0.7.9-2?arch=amd64&distro=debian-10.13",
      "type": "library",
      "bom-ref": "BomRef.3869128736837293.6257884752608595",
      "version": "unknown"
    },
    {
      "name": "pkg:deb/debian/libcom-err2@1.44.5-1%2Bdeb10u3?arch=amd64&distro=debian-10.13",
      "type": "library",
      "bom-ref": "BomRef.6461871919153933.8617442202419534",
      "version": "unknown"
    },
    {
      "name": "pkg:deb/debian/libdb5.3@5.3.28%2Bdfsg1-0.5?arch=amd64&distro=debian-10.13",
      "type": "library",
      "bom-ref": "BomRef.1630805667647005.9612261805115973",
      "version": "unknown"
    },
    {
      "name": "pkg:deb/debian/libdebconfclient0@0.249?arch=amd64&distro=debian-10.13",
      "type": "library",
      "bom-ref": "BomRef.550785804982093.10127053264786345",
      "version": "unknown"
    },
    {
      "name": "pkg:deb/debian/libexpat1@2.2.6-2%2Bdeb10u6?arch=amd64&distro=debian-10.13",
      "type": "library",
      "bom-ref": "BomRef.13250285171522214.675576239145853",
      "version": "unknown"
    },
    {
      "name": "pkg:deb/debian/libext2fs2@1.44.5-1%2Bdeb10u3?arch=amd64&distro=debian-10.13",
      "type": "library",
      "bom-ref": "BomRef.5613002246007827.6119006796626725",
      "version": "unknown"
    },
    {
      "name": "pkg:deb/debian/libfdisk1@2.33.1-0.1?arch=amd64&distro=debian-10.13",
      "type": "library",
      "bom-ref": "BomRef.5179958314467142.3549960351876331",
      "version": "unknown"
    },
    {
      "name": "pkg:deb/debian/libffi6@3.2.1-9?arch=amd64&distro=debian-10.13",
      "type": "library",
      "bom-ref": "BomRef.23464900381636478.9588109141488649",
      "version": "unknown"
    },
    {
      "name": "pkg:deb/debian/libgcc1@8.3.0-6?arch=amd64&distro=debian-10.13&epoch=1",
      "type": "library",
      "bom-ref": "BomRef.44509529499573575.44837303868287604",
      "version": "unknown"
    },
    {
      "name": "pkg:deb/debian/libgcrypt20@1.8.4-5%2Bdeb10u1?arch=amd64&distro=debian-10.13",
      "type": "library",
      "bom-ref": "BomRef.09990318247266972.5687852289620989",
      "version": "unknown"
    },
    {
      "name": "pkg:deb/debian/libgdbm6@1.18.1-4?arch=amd64&distro=debian-10.13",
      "type": "library",
      "bom-ref": "BomRef.7683957878084051.3107968656395772",
      "version": "unknown"
    },
    {
      "name": "pkg:deb/debian/libgmp10@6.1.2%2Bdfsg-4%2Bdeb10u1?arch=amd64&distro=debian-10.13&epoch=2",
      "type": "library",
      "bom-ref": "BomRef.7539142572809187.5560758331770689",
      "version": "unknown"
    },
    {
      "name": "pkg:deb/debian/libgnutls30@3.6.7-4%2Bdeb10u10?arch=amd64&distro=debian-10.13",
      "type": "library",
      "bom-ref": "BomRef.6361768495305822.6711137831604322",
      "version": "unknown"
    },
    {
      "name": "pkg:deb/debian/libgpg-error0@1.35-1?arch=amd64&distro=debian-10.13",
      "type": "library",
      "bom-ref": "BomRef.20735456564719268.8368899089653618",
      "version": "unknown"
    },
    {
      "name": "pkg:deb/debian/libhogweed4@3.4.1-1%2Bdeb10u1?arch=amd64&distro=debian-10.13",
      "type": "library",
      "bom-ref": "BomRef.6616732750838527.40391962120154457",
      "version": "unknown"
    },
    {
      "name": "pkg:deb/debian/libidn2-0@2.0.5-1%2Bdeb10u1?arch=amd64&distro=debian-10.13",
      "type": "library",
      "bom-ref": "BomRef.6715849278093826.11832111772623899",
      "version": "unknown"
    },
    {
      "name": "pkg:deb/debian/liblz4-1@1.8.3-1%2Bdeb10u1?arch=amd64&distro=debian-10.13",
      "type": "library",
      "bom-ref": "BomRef.7701865990796456.8732878638808677",
      "version": "unknown"
    },
    {
      "name": "pkg:deb/debian/liblzma5@5.2.4-1%2Bdeb10u1?arch=amd64&distro=debian-10.13",
      "type": "library",
      "bom-ref": "BomRef.8447076522257173.6649265903109479",
      "version": "unknown"
    },
    {
      "name": "pkg:deb/debian/libmount1@2.33.1-0.1?arch=amd64&distro=debian-10.13",
      "type": "library",
      "bom-ref": "BomRef.6956986612397928.5285092195227085",
      "version": "unknown"
    },
    {
      "name": "pkg:deb/debian/libncursesw6@6.1%2B20181013-2%2Bdeb10u3?arch=amd64&distro=debian-10.13",
      "type": "library",
      "bom-ref": "BomRef.4091660324565164.21420713463326213",
      "version": "unknown"
    },
    {
      "name": "pkg:deb/debian/libnettle6@3.4.1-1%2Bdeb10u1?arch=amd64&distro=debian-10.13",
      "type": "library",
      "bom-ref": "BomRef.2102440266023361.6975925320332383",
      "version": "unknown"
    },
    {
      "name": "pkg:deb/debian/libp11-kit0@0.23.15-2%2Bdeb10u1?arch=amd64&distro=debian-10.13",
      "type": "library",
      "bom-ref": "BomRef.10622035543428843.8288101703750075",
      "version": "unknown"
    },
    {
      "name": "pkg:deb/debian/libpam-modules-bin@1.3.1-5?arch=amd64&distro=debian-10.13",
      "type": "library",
      "bom-ref": "BomRef.22548833402309776.8115158357035026",
      "version": "unknown"
    },
    {
      "name": "pkg:deb/debian/libpam-modules@1.3.1-5?arch=amd64&distro=debian-10.13",
      "type": "library",
      "bom-ref": "BomRef.9257064915885521.8888201392571667",
      "version": "unknown"
    },
    {
      "name": "pkg:deb/debian/libpam-runtime@1.3.1-5?arch=all&distro=debian-10.13",
      "type": "library",
      "bom-ref": "BomRef.4065717871121364.8805913115689622",
      "version": "unknown"
    },
    {
      "name": "pkg:deb/debian/libpam0g@1.3.1-5?arch=amd64&distro=debian-10.13",
      "type": "library",
      "bom-ref": "BomRef.9145901084243218.6612527534160212",
      "version": "unknown"
    },
    {
      "name": "pkg:deb/debian/libpcre3@8.39-12?arch=amd64&distro=debian-10.13&epoch=2",
      "type": "library",
      "bom-ref": "BomRef.18244312325019596.666493208367062",
      "version": "unknown"
    },
    {
      "name": "pkg:deb/debian/libreadline7@7.0-5?arch=amd64&distro=debian-10.13",
      "type": "library",
      "bom-ref": "BomRef.8245473248354268.3897109391139155",
      "version": "unknown"
    },
    {
      "name": "pkg:deb/debian/libseccomp2@2.3.3-4?arch=amd64&distro=debian-10.13",
      "type": "library",
      "bom-ref": "BomRef.7768687069096483.9059031606134436",
      "version": "unknown"
    },
    {
      "name": "pkg:deb/debian/libselinux1@2.8-1%2Bb1?arch=amd64&distro=debian-10.13",
      "type": "library",
      "bom-ref": "BomRef.3294059507300273.15730495702572544",
      "version": "unknown"
    },
    {
      "name": "pkg:deb/debian/libsemanage-common@2.8-2?arch=all&distro=debian-10.13",
      "type": "library",
      "bom-ref": "BomRef.4170314953330493.8979008838292658",
      "version": "unknown"
    },
    {
      "name": "pkg:deb/debian/libsemanage1@2.8-2?arch=amd64&distro=debian-10.13",
      "type": "library",
      "bom-ref": "BomRef.6436830363595765.7826584156905563",
      "version": "unknown"
    },
    {
      "name": "pkg:deb/debian/libsepol1@2.8-1?arch=amd64&distro=debian-10.13",
      "type": "library",
      "bom-ref": "BomRef.1082568500459854.6514621987537436",
      "version": "unknown"
    },
    {
      "name": "pkg:deb/debian/libsmartcols1@2.33.1-0.1?arch=amd64&distro=debian-10.13",
      "type": "library",
      "bom-ref": "BomRef.7074350732166196.44057148635044474",
      "version": "unknown"
    },
    {
      "name": "pkg:deb/debian/libsqlite3-0@3.27.2-3%2Bdeb10u2?arch=amd64&distro=debian-10.13",
      "type": "library",
      "bom-ref": "BomRef.02246905311535452.06354921754141207",
      "version": "unknown"
    },
    {
      "name": "pkg:deb/debian/libss2@1.44.5-1%2Bdeb10u3?arch=amd64&distro=debian-10.13",
      "type": "library",
      "bom-ref": "BomRef.2120281883419497.6309704549188189",
      "version": "unknown"
    },
    {
      "name": "pkg:deb/debian/libssl1.1@1.1.1n-0%2Bdeb10u5?arch=amd64&distro=debian-10.13",
      "type": "library",
      "bom-ref": "BomRef.9410151172061264.8843244541421621",
      "version": "unknown"
    },
    {
      "name": "pkg:deb/debian/libstdc%2B%2B6@8.3.0-6?arch=amd64&distro=debian-10.13",
      "type": "library",
      "bom-ref": "BomRef.17076814296051945.6374778104445937",
      "version": "unknown"
    },
    {
      "name": "pkg:deb/debian/libsystemd0@241-7~deb10u9?arch=amd64&distro=debian-10.13",
      "type": "library",
      "bom-ref": "BomRef.08916256007429224.20222460103543738",
      "version": "unknown"
    },
    {
      "name": "pkg:deb/debian/libtasn1-6@4.13-3%2Bdeb10u1?arch=amd64&distro=debian-10.13",
      "type": "library",
      "bom-ref": "BomRef.031696551291047426.10396121084520848",
      "version": "unknown"
    },
    {
      "name": "pkg:deb/debian/libtinfo6@6.1%2B20181013-2%2Bdeb10u3?arch=amd64&distro=debian-10.13",
      "type": "library",
      "bom-ref": "BomRef.08313308033939204.1910863659872465",
      "version": "unknown"
    },
    {
      "name": "pkg:deb/debian/libudev1@241-7~deb10u9?arch=amd64&distro=debian-10.13",
      "type": "library",
      "bom-ref": "BomRef.33016507425958097.1690517201542352",
      "version": "unknown"
    },
    {
      "name": "pkg:deb/debian/libunistring2@0.9.10-1?arch=amd64&distro=debian-10.13",
      "type": "library",
      "bom-ref": "BomRef.8860575969429222.40219277227653494",
      "version": "unknown"
    },
    {
      "name": "pkg:deb/debian/libuuid1@2.33.1-0.1?arch=amd64&distro=debian-10.13",
      "type": "library",
      "bom-ref": "BomRef.9300099223985805.15576694339990138",
      "version": "unknown"
    },
    {
      "name": "pkg:deb/debian/libzstd1@1.3.8%2Bdfsg-3%2Bdeb10u2?arch=amd64&distro=debian-10.13",
      "type": "library",
      "bom-ref": "BomRef.6840628986499657.35054026048764364",
      "version": "unknown"
    },
    {
      "name": "pkg:deb/debian/login@4.5-1.1?arch=amd64&distro=debian-10.13&epoch=1",
      "type": "library",
      "bom-ref": "BomRef.711061371436041.30278103253409994",
      "version": "unknown"
    },
    {
      "name": "pkg:deb/debian/mawk@1.3.3-17%2Bb3?arch=amd64&distro=debian-10.13",
      "type": "library",
      "bom-ref": "BomRef.48643757647976626.5002721778519085",
      "version": "unknown"
    },
    {
      "name": "pkg:deb/debian/mount@2.33.1-0.1?arch=amd64&distro=debian-10.13",
      "type": "library",
      "bom-ref": "BomRef.2385735608781827.6097038738075407",
      "version": "unknown"
    },
    {
      "name": "pkg:deb/debian/ncurses-base@6.1%2B20181013-2%2Bdeb10u3?arch=all&distro=debian-10.13",
      "type": "library",
      "bom-ref": "BomRef.9256762894378713.7550730583015919",
      "version": "unknown"
    },
    {
      "name": "pkg:deb/debian/ncurses-bin@6.1%2B20181013-2%2Bdeb10u3?arch=amd64&distro=debian-10.13",
      "type": "library",
      "bom-ref": "BomRef.7079434540667284.47839905752566425",
      "version": "unknown"
    },
    {
      "name": "pkg:deb/debian/netbase@5.6?arch=all&distro=debian-10.13",
      "type": "library",
      "bom-ref": "BomRef.20360003149202588.42861496072108307",
      "version": "unknown"
    },
    {
      "name": "pkg:deb/debian/openssl@1.1.1n-0%2Bdeb10u5?arch=amd64&distro=debian-10.13",
      "type": "library",
      "bom-ref": "BomRef.3806047727413433.505295299490189",
      "version": "unknown"
    },
    {
      "name": "pkg:deb/debian/passwd@4.5-1.1?arch=amd64&distro=debian-10.13&epoch=1",
      "type": "library",
      "bom-ref": "BomRef.032593520394859965.6636310988249421",
      "version": "unknown"
    },
    {
      "name": "pkg:deb/debian/perl-base@5.28.1-6%2Bdeb10u1?arch=amd64&distro=debian-10.13",
      "type": "library",
      "bom-ref": "BomRef.5335256560698366.5760334396406162",
      "version": "unknown"
    },
    {
      "name": "pkg:deb/debian/readline-common@7.0-5?arch=all&distro=debian-10.13",
      "type": "library",
      "bom-ref": "BomRef.27925021347102796.5720788753540428",
      "version": "unknown"
    },
    {
      "name": "pkg:deb/debian/sed@4.7-1?arch=amd64&distro=debian-10.13",
      "type": "library",
      "bom-ref": "BomRef.42277986972293635.7924945142482447",
      "version": "unknown"
    },
    {
      "name": "pkg:deb/debian/sysvinit-utils@2.93-8?arch=amd64&distro=debian-10.13",
      "type": "library",
      "bom-ref": "BomRef.4878844544766262.06714786934780592",
      "version": "unknown"
    },
    {
      "name": "pkg:deb/debian/tar@1.30%2Bdfsg-6?arch=amd64&distro=debian-10.13",
      "type": "library",
      "bom-ref": "BomRef.4144973113739717.665584805649605",
      "version": "unknown"
    },
    {
      "name": "pkg:deb/debian/tzdata@2021a-0%2Bdeb10u11?arch=all&distro=debian-10.13",
      "type": "library",
      "bom-ref": "BomRef.1587968807596697.5056018627841146",
      "version": "unknown"
    },
    {
      "name": "pkg:deb/debian/util-linux@2.33.1-0.1?arch=amd64&distro=debian-10.13",
      "type": "library",
      "bom-ref": "BomRef.6807783914099673.9165622743737247",
      "version": "unknown"
    },
    {
      "name": "pkg:deb/debian/zlib1g@1.2.11.dfsg-1%2Bdeb10u2?arch=amd64&distro=debian-10.13&epoch=1",
      "type": "library",
      "bom-ref": "BomRef.20739971742141883.3001387951362695",
      "version": "unknown"
    },
    {
      "name": "pkg:oci/python@sha256%3A320a7a4250aba4249f458872adecf92eea88dc6abd2d76dc5c0f01cac9b53990?arch=amd64&repository_url=index.docker.io%2Flibrary%2Fpython",
      "type": "library",
      "bom-ref": "BomRef.756797627908924.5219825998768215",
      "version": "unknown"
    },
    {
      "name": "pkg:pypi/pip@23.0.1",
      "type": "library",
      "bom-ref": "BomRef.9246923334536788.6968494281367785",
      "version": "unknown"
    },
    {
      "name": "pkg:pypi/setuptools@58.1.0",
      "type": "library",
      "bom-ref": "BomRef.4697178893250725.4583198029933888",
      "version": "unknown"
    },
    {
      "name": "pkg:pypi/wheel@0.40.0",
      "type": "library",
      "bom-ref": "BomRef.6147799166430863.8548445589757568",
      "version": "unknown"
    },
    {
      "name": "readline-common",
      "type": "library",
      "bom-ref": "BomRef.47037917441450017.5465952145366529",
      "version": "7.0-5"
    },
    {
      "name": "sed",
      "type": "library",
      "bom-ref": "BomRef.09960071760420075.9412489640509445",
      "version": "4.7-1"
    },
    {
      "name": "setuptools",
      "type": "library",
      "bom-ref": "BomRef.9222636214316768.10200663387594888",
      "version": "58.1.0"
    },
    {
      "name": "sysvinit-utils",
      "type": "library",
      "bom-ref": "BomRef.8585578608123942.496774057818847",
      "version": "2.93-8"
    },
    {
      "name": "tar",
      "type": "library",
      "bom-ref": "BomRef.8092599558296774.21031271577614796",
      "version": "1.30+dfsg-6"
    },
    {
      "name": "tzdata",
      "type": "library",
      "bom-ref": "BomRef.503573230370145.08318753025020353",
      "version": "2021a-0+deb10u11"
    },
    {
      "name": "util-linux",
      "type": "library",
      "bom-ref": "BomRef.1260226674627386.38314071382193016",
      "version": "2.33.1-0.1"
    },
    {
      "name": "wheel",
      "type": "library",
      "bom-ref": "BomRef.004457715120494532.263181130091072",
      "version": "0.40.0"
    },
    {
      "name": "zlib1g",
      "type": "library",
      "bom-ref": "BomRef.3226593072210092.14307264864762748",
      "version": "1:1.2.11.dfsg-1+deb10u2"
    }
  ],
  "specVersion": "1.6",
  "dependencies": [
    {
      "ref": "BomRef.6176396336955146.7344873491266293"
    },
    {
      "ref": "BomRef.9243611090117512.47714167587276113"
    },
    {
      "ref": "BomRef.5274394552679859.8445427415265542"
    },
    {
      "ref": "BomRef.2967330057897104.5040741558506687"
    },
    {
      "ref": "BomRef.9861438969360008.5012638479741188"
    },
    {
      "ref": "BomRef.8522141329258298.9346347482229125"
    },
    {
      "ref": "BomRef.9431523444773862.48301525597665396"
    },
    {
      "ref": "BomRef.07781830204959628.04339280253173139"
    },
    {
      "ref": "BomRef.8661634751568574.9339051917710173"
    },
    {
      "ref": "BomRef.936449302980033.8545499211546351"
    },
    {
      "ref": "BomRef.7526493208645537.02383917188472129"
    },
    {
      "ref": "BomRef.0006152465802201634.4631536434983474"
    },
    {
      "ref": "BomRef.7207167623331593.45235921348010955"
    },
    {
      "ref": "BomRef.2728436378390051.9249776559314489"
    },
    {
      "ref": "BomRef.2897300372502959.9312535430593759"
    },
    {
      "ref": "BomRef.6838340901315719.9157372342516404"
    },
    {
      "ref": "BomRef.684453649653739.6597726156523075"
    },
    {
      "ref": "BomRef.7116479712211018.7517733506180486"
    },
    {
      "ref": "BomRef.07281602366116657.6243025962737354"
    },
    {
      "ref": "BomRef.18183696370020264.4088028993540581"
    },
    {
      "ref": "BomRef.5722608417861503.6527072754481692"
    },
    {
      "ref": "BomRef.431931804549218.06703505513618213"
    },
    {
      "ref": "BomRef.6905480172641373.11068904079134823"
    },
    {
      "ref": "BomRef.9267275828375128.6770824946557062"
    },
    {
      "ref": "BomRef.9174858123595855.07159214189561325"
    },
    {
      "ref": "BomRef.9123630239172172.4772858501637405"
    },
    {
      "ref": "BomRef.28673386609622875.11670208602889987"
    },
    {
      "ref": "BomRef.31296870280502054.3681329725059911"
    },
    {
      "ref": "BomRef.13420312221791275.9566188980831586"
    },
    {
      "ref": "BomRef.06788697139426092.30307873955849707"
    },
    {
      "ref": "BomRef.4776024341063957.7550766671423965"
    },
    {
      "ref": "BomRef.29299669173162535.8957049923898667"
    },
    {
      "ref": "BomRef.5965573119036772.9456242921041607"
    },
    {
      "ref": "BomRef.3869128736837293.6257884752608595"
    },
    {
      "ref": "BomRef.6461871919153933.8617442202419534"
    },
    {
      "ref": "BomRef.1630805667647005.9612261805115973"
    },
    {
      "ref": "BomRef.550785804982093.10127053264786345"
    },
    {
      "ref": "BomRef.13250285171522214.675576239145853"
    },
    {
      "ref": "BomRef.5613002246007827.6119006796626725"
    },
    {
      "ref": "BomRef.5179958314467142.3549960351876331"
    },
    {
      "ref": "BomRef.23464900381636478.9588109141488649"
    },
    {
      "ref": "BomRef.44509529499573575.44837303868287604"
    },
    {
      "ref": "BomRef.09990318247266972.5687852289620989"
    },
    {
      "ref": "BomRef.7683957878084051.3107968656395772"
    },
    {
      "ref": "BomRef.7539142572809187.5560758331770689"
    },
    {
      "ref": "BomRef.6361768495305822.6711137831604322"
    },
    {
      "ref": "BomRef.20735456564719268.8368899089653618"
    },
    {
      "ref": "BomRef.6616732750838527.40391962120154457"
    },
    {
      "ref": "BomRef.6715849278093826.11832111772623899"
    },
    {
      "ref": "BomRef.7701865990796456.8732878638808677"
    },
    {
      "ref": "BomRef.8447076522257173.6649265903109479"
    },
    {
      "ref": "BomRef.6956986612397928.5285092195227085"
    },
    {
      "ref": "BomRef.4091660324565164.21420713463326213"
    },
    {
      "ref": "BomRef.2102440266023361.6975925320332383"
    },
    {
      "ref": "BomRef.10622035543428843.8288101703750075"
    },
    {
      "ref": "BomRef.22548833402309776.8115158357035026"
    },
    {
      "ref": "BomRef.9257064915885521.8888201392571667"
    },
    {
      "ref": "BomRef.4065717871121364.8805913115689622"
    },
    {
      "ref": "BomRef.9145901084243218.6612527534160212"
    },
    {
      "ref": "BomRef.18244312325019596.666493208367062"
    },
    {
      "ref": "BomRef.8245473248354268.3897109391139155"
    },
    {
      "ref": "BomRef.7768687069096483.9059031606134436"
    },
    {
      "ref": "BomRef.3294059507300273.15730495702572544"
    },
    {
      "ref": "BomRef.4170314953330493.8979008838292658"
    },
    {
      "ref": "BomRef.6436830363595765.7826584156905563"
    },
    {
      "ref": "BomRef.1082568500459854.6514621987537436"
    },
    {
      "ref": "BomRef.7074350732166196.44057148635044474"
    },
    {
      "ref": "BomRef.02246905311535452.06354921754141207"
    },
    {
      "ref": "BomRef.2120281883419497.6309704549188189"
    },
    {
      "ref": "BomRef.9410151172061264.8843244541421621"
    },
    {
      "ref": "BomRef.17076814296051945.6374778104445937"
    },
    {
      "ref": "BomRef.08916256007429224.20222460103543738"
    },
    {
      "ref": "BomRef.031696551291047426.10396121084520848"
    },
    {
      "ref": "BomRef.08313308033939204.1910863659872465"
    },
    {
      "ref": "BomRef.33016507425958097.1690517201542352"
    },
    {
      "ref": "BomRef.8860575969429222.40219277227653494"
    },
    {
      "ref": "BomRef.9300099223985805.15576694339990138"
    },
    {
      "ref": "BomRef.6840628986499657.35054026048764364"
    },
    {
      "ref": "BomRef.711061371436041.30278103253409994"
    },
    {
      "ref": "BomRef.48643757647976626.5002721778519085"
    },
    {
      "ref": "BomRef.2385735608781827.6097038738075407"
    },
    {
      "ref": "BomRef.9256762894378713.7550730583015919"
    },
    {
      "ref": "BomRef.7079434540667284.47839905752566425"
    },
    {
      "ref": "BomRef.20360003149202588.42861496072108307"
    },
    {
      "ref": "BomRef.3806047727413433.505295299490189"
    },
    {
      "ref": "BomRef.032593520394859965.6636310988249421"
    },
    {
      "ref": "BomRef.5335256560698366.5760334396406162"
    },
    {
      "ref": "BomRef.27925021347102796.5720788753540428"
    },
    {
      "ref": "BomRef.42277986972293635.7924945142482447"
    },
    {
      "ref": "BomRef.4878844544766262.06714786934780592"
    },
    {
      "ref": "BomRef.4144973113739717.665584805649605"
    },
    {
      "ref": "BomRef.1587968807596697.5056018627841146"
    },
    {
      "ref": "BomRef.6807783914099673.9165622743737247"
    },
    {
      "ref": "BomRef.20739971742141883.3001387951362695"
    },
    {
      "ref": "BomRef.756797627908924.5219825998768215"
    },
    {
      "ref": "BomRef.9246923334536788.6968494281367785"
    },
    {
      "ref": "BomRef.4697178893250725.4583198029933888"
    },
    {
      "ref": "BomRef.6147799166430863.8548445589757568"
    },
    {
      "ref": "BomRef.4106548171771164.40345315035365337"
    },
    {
      "ref": "BomRef.5764489436016302.11966297497559053"
    },
    {
      "ref": "BomRef.2091561318312628.10533641099039537"
    },
    {
      "ref": "BomRef.5285899786206747.39893870367851547"
    },
    {
      "ref": "BomRef.19632902380378148.7674190403644553"
    },
    {
      "ref": "BomRef.08044540296163805.6074878777255607"
    },
    {
      "ref": "BomRef.19697092205222.4114747644816703"
    },
    {
      "ref": "BomRef.7835375189870991.9714073481058098"
    },
    {
      "ref": "BomRef.123298693870599.28454743690470186"
    },
    {
      "ref": "BomRef.21872175349675793.21978558774826173"
    },
    {
      "ref": "BomRef.7231334427763637.7970442731868245"
    },
    {
      "ref": "BomRef.49943365452815924.574184867203909"
    },
    {
      "ref": "BomRef.007838730168462704.04960075241039086"
    },
    {
      "ref": "BomRef.9381702685953822.8704276567702453"
    },
    {
      "ref": "BomRef.39041126673773086.5934036822798651"
    },
    {
      "ref": "BomRef.8087205421834798.12970919873885822"
    },
    {
      "ref": "BomRef.13779902434842395.07571395197316111"
    },
    {
      "ref": "BomRef.23493549977876682.8226606810817382"
    },
    {
      "ref": "BomRef.3950435385749209.9713751141431759"
    },
    {
      "ref": "BomRef.5231310262223396.6296323553660003"
    },
    {
      "ref": "BomRef.6944009531744872.423455455135313"
    },
    {
      "ref": "BomRef.06246220426837246.38047467679875757"
    },
    {
      "ref": "BomRef.3159739788366621.9573437779759497"
    },
    {
      "ref": "BomRef.5484736261483107.35607144113402145"
    },
    {
      "ref": "BomRef.3170287804189975.8581828672652744"
    },
    {
      "ref": "BomRef.7589394888738071.5676067692913361"
    },
    {
      "ref": "BomRef.31741350102540533.13132463919420412"
    },
    {
      "ref": "BomRef.9711466857540676.2231529081764385"
    },
    {
      "ref": "BomRef.4285357051314367.28625519667125443"
    },
    {
      "ref": "BomRef.4717716494577069.31419335513246105"
    },
    {
      "ref": "BomRef.3022033642181272.10541805158756778"
    },
    {
      "ref": "BomRef.8074508612901721.5349819479162559"
    },
    {
      "ref": "BomRef.8170352054673204.45266508153759977"
    },
    {
      "ref": "BomRef.7970489706159132.7621623219385009"
    },
    {
      "ref": "BomRef.8661478586184156.7845309765155044"
    },
    {
      "ref": "BomRef.8226914678415594.25588819524503914"
    },
    {
      "ref": "BomRef.6611298573963369.5741563291771412"
    },
    {
      "ref": "BomRef.09728070518796805.6425828489493881"
    },
    {
      "ref": "BomRef.7800340428531145.7613589707345659"
    },
    {
      "ref": "BomRef.8734399927920087.007389040746614839"
    },
    {
      "ref": "BomRef.03135848170111033.07351886946086106"
    },
    {
      "ref": "BomRef.2661655399555968.26106285153227726"
    },
    {
      "ref": "BomRef.48183529112695056.5379591155799494"
    },
    {
      "ref": "BomRef.6113324167968318.26932352046523056"
    },
    {
      "ref": "BomRef.7533192798023765.14660906261556617"
    },
    {
      "ref": "BomRef.2642346134690531.07941861698216335"
    },
    {
      "ref": "BomRef.14447900021030913.5050481265260169"
    },
    {
      "ref": "BomRef.589653529997073.5229953429927768"
    },
    {
      "ref": "BomRef.8117423853886457.4648140235794761"
    },
    {
      "ref": "BomRef.6851599695313291.08990890399812401"
    },
    {
      "ref": "BomRef.843847496965296.7511672660256941"
    },
    {
      "ref": "BomRef.21307869203310903.5315082586911285"
    },
    {
      "ref": "BomRef.8981094158029495.9035551035035969"
    },
    {
      "ref": "BomRef.14816770679843028.3553849695854441"
    },
    {
      "ref": "BomRef.2272886416556048.12388153118869705"
    },
    {
      "ref": "BomRef.2667887207665496.7341866808898544"
    },
    {
      "ref": "BomRef.8469338240067857.047269724613064446"
    },
    {
      "ref": "BomRef.12837962734449626.05534387675259855"
    },
    {
      "ref": "BomRef.5345454605247784.20220601551008066"
    },
    {
      "ref": "BomRef.41206197383737364.3468607874589076"
    },
    {
      "ref": "BomRef.7696861557576261.3318395440957952"
    },
    {
      "ref": "BomRef.2683506269789242.7243998880253915"
    },
    {
      "ref": "BomRef.6429455295562106.7064314295365873"
    },
    {
      "ref": "BomRef.1825685027184697.005724517540941831"
    },
    {
      "ref": "BomRef.9137893926473654.9865446889174417"
    },
    {
      "ref": "BomRef.3978305772391917.14039325714478323"
    },
    {
      "ref": "BomRef.27152506136280485.1935197351032666"
    },
    {
      "ref": "BomRef.5506495027418566.2784048376638487"
    },
    {
      "ref": "BomRef.7795371118756164.3457972843468424"
    },
    {
      "ref": "BomRef.9414875880166151.4959548383628055"
    },
    {
      "ref": "BomRef.9312106539908698.23572848170581295"
    },
    {
      "ref": "BomRef.5417366821428413.1438590947874785"
    },
    {
      "ref": "BomRef.15062815171974941.724007452379435"
    },
    {
      "ref": "BomRef.7841101856428094.49191235980057746"
    },
    {
      "ref": "BomRef.5445025828491711.48712032812716544"
    },
    {
      "ref": "BomRef.3954637679877454.4215398480724897"
    },
    {
      "ref": "BomRef.7845302580394067.5391425268250879"
    },
    {
      "ref": "BomRef.1100663801705305.9598521082996869"
    },
    {
      "ref": "BomRef.7310717039694602.29386248113252045"
    },
    {
      "ref": "BomRef.47805142558440994.27285780335907417"
    },
    {
      "ref": "BomRef.3830330187021158.6044547888756708"
    },
    {
      "ref": "BomRef.3083430203319103.9208606227334225"
    },
    {
      "ref": "BomRef.4469121080242916.1622680119779809"
    },
    {
      "ref": "BomRef.25440448789280723.4391424255841939"
    },
    {
      "ref": "BomRef.6268911726585615.04840601523020027"
    },
    {
      "ref": "BomRef.6846444710357533.8024111595128504"
    },
    {
      "ref": "BomRef.6220556903779093.005414770566189664"
    },
    {
      "ref": "BomRef.403700319377266.12738586110437944"
    },
    {
      "ref": "BomRef.47037917441450017.5465952145366529"
    },
    {
      "ref": "BomRef.09960071760420075.9412489640509445"
    },
    {
      "ref": "BomRef.9222636214316768.10200663387594888"
    },
    {
      "ref": "BomRef.8585578608123942.496774057818847"
    },
    {
      "ref": "BomRef.8092599558296774.21031271577614796"
    },
    {
      "ref": "BomRef.503573230370145.08318753025020353"
    },
    {
      "ref": "BomRef.1260226674627386.38314071382193016"
    },
    {
      "ref": "BomRef.004457715120494532.263181130091072"
    },
    {
      "ref": "BomRef.3226593072210092.14307264864762748"
    },
    {
      "ref": "pkg:oci/python@3.9-slim-buster?digest=sha256:320a7a4250aba4249f458872adecf92eea88dc6abd2d76dc5c0f01cac9b53990",
      "dependsOn": [
        "BomRef.9145901084243218.6612527534160212",
        "BomRef.9267275828375128.6770824946557062",
        "BomRef.6436830363595765.7826584156905563",
        "BomRef.6147799166430863.8548445589757568",
        "BomRef.20735456564719268.8368899089653618",
        "BomRef.5965573119036772.9456242921041607",
        "BomRef.29299669173162535.8957049923898667",
        "BomRef.44509529499573575.44837303868287604",
        "BomRef.4697178893250725.4583198029933888",
        "BomRef.42277986972293635.7924945142482447",
        "BomRef.2967330057897104.5040741558506687",
        "BomRef.2120281883419497.6309704549188189",
        "BomRef.13250285171522214.675576239145853",
        "BomRef.4065717871121364.8805913115689622",
        "BomRef.20739971742141883.3001387951362695",
        "BomRef.5722608417861503.6527072754481692",
        "BomRef.4878844544766262.06714786934780592",
        "BomRef.936449302980033.8545499211546351",
        "BomRef.9256762894378713.7550730583015919",
        "BomRef.4091660324565164.21420713463326213",
        "BomRef.18183696370020264.4088028993540581",
        "BomRef.7701865990796456.8732878638808677",
        "BomRef.33016507425958097.1690517201542352",
        "BomRef.3806047727413433.505295299490189",
        "BomRef.4170314953330493.8979008838292658",
        "BomRef.06788697139426092.30307873955849707",
        "BomRef.8245473248354268.3897109391139155",
        "BomRef.7683957878084051.3107968656395772",
        "BomRef.09990318247266972.5687852289620989",
        "BomRef.756797627908924.5219825998768215",
        "BomRef.6905480172641373.11068904079134823",
        "BomRef.6715849278093826.11832111772623899",
        "BomRef.9300099223985805.15576694339990138",
        "BomRef.9257064915885521.8888201392571667",
        "BomRef.6840628986499657.35054026048764364",
        "BomRef.7074350732166196.44057148635044474",
        "BomRef.10622035543428843.8288101703750075",
        "BomRef.22548833402309776.8115158357035026",
        "BomRef.6838340901315719.9157372342516404",
        "BomRef.7526493208645537.02383917188472129",
        "BomRef.23464900381636478.9588109141488649",
        "BomRef.9431523444773862.48301525597665396",
        "BomRef.9174858123595855.07159214189561325",
        "BomRef.9243611090117512.47714167587276113",
        "BomRef.08916256007429224.20222460103543738",
        "BomRef.8522141329258298.9346347482229125",
        "BomRef.2385735608781827.6097038738075407",
        "BomRef.1587968807596697.5056018627841146",
        "BomRef.07281602366116657.6243025962737354",
        "BomRef.5179958314467142.3549960351876331",
        "BomRef.20360003149202588.42861496072108307",
        "BomRef.17076814296051945.6374778104445937",
        "BomRef.07781830204959628.04339280253173139",
        "BomRef.7539142572809187.5560758331770689",
        "BomRef.9861438969360008.5012638479741188",
        "BomRef.4776024341063957.7550766671423965",
        "BomRef.550785804982093.10127053264786345",
        "BomRef.5613002246007827.6119006796626725",
        "BomRef.8860575969429222.40219277227653494",
        "BomRef.711061371436041.30278103253409994",
        "BomRef.6176396336955146.7344873491266293",
        "BomRef.5274394552679859.8445427415265542",
        "BomRef.6361768495305822.6711137831604322",
        "BomRef.7207167623331593.45235921348010955",
        "BomRef.13420312221791275.9566188980831586",
        "BomRef.6461871919153933.8617442202419534",
        "BomRef.3869128736837293.6257884752608595",
        "BomRef.7116479712211018.7517733506180486",
        "BomRef.08313308033939204.1910863659872465",
        "BomRef.18244312325019596.666493208367062",
        "BomRef.6956986612397928.5285092195227085",
        "BomRef.48643757647976626.5002721778519085",
        "BomRef.431931804549218.06703505513618213",
        "BomRef.8661634751568574.9339051917710173",
        "BomRef.9246923334536788.6968494281367785",
        "BomRef.28673386609622875.11670208602889987",
        "BomRef.6616732750838527.40391962120154457",
        "BomRef.032593520394859965.6636310988249421",
        "BomRef.4144973113739717.665584805649605",
        "BomRef.6807783914099673.9165622743737247",
        "BomRef.31296870280502054.3681329725059911",
        "BomRef.1082568500459854.6514621987537436",
        "BomRef.02246905311535452.06354921754141207",
        "BomRef.7079434540667284.47839905752566425",
        "BomRef.27925021347102796.5720788753540428",
        "BomRef.1630805667647005.9612261805115973",
        "BomRef.031696551291047426.10396121084520848",
        "BomRef.684453649653739.6597726156523075",
        "BomRef.8447076522257173.6649265903109479",
        "BomRef.0006152465802201634.4631536434983474",
        "BomRef.5335256560698366.5760334396406162",
        "BomRef.2102440266023361.6975925320332383",
        "BomRef.9123630239172172.4772858501637405",
        "BomRef.9410151172061264.8843244541421621",
        "BomRef.7768687069096483.9059031606134436",
        "BomRef.2728436378390051.9249776559314489",
        "BomRef.2897300372502959.9312535430593759",
        "BomRef.3294059507300273.15730495702572544"
      ]
    }
  ],
  "serialNumber": "urn:uuid:883a19c3-8eb6-47b1-b4f4-6ae81bc6688e"
}